modulare/__init__.py
modulare/logger.py
modulare/decorators/__init__.py
modulare/decorators/http/__init__.py
modulare/decorators/http/route_decorator.py
modulare/decorators/http/status_code_decorator.py
modulare/decorators/http/constants/route_decorator_constant.py
modulare/decorators/http/enums/status_code_decorator_enum.py
modulare/decorators/module/__init__.py
modulare/decorators/module/module_decorator.py
modulare/factories/application_factory.py
modulare/http/http_server.py
modulare/utils/partial_class.py
sample/01-basic-crud/.gitignore
sample/01-basic-crud/Makefile
sample/01-basic-crud/README.md
sample/01-basic-crud/pyproject.toml
sample/01-basic-crud/src/main.py
sample/01-basic-crud/src/infraestructure/containers.py
sample/01-basic-crud/src/modules/app/app_controller.py
sample/01-basic-crud/src/modules/app/app_module.py
sample/01-basic-crud/src/modules/app/app_service.py
sample/01-basic-crud/src/modules/caller/caller_1_service.py
sample/01-basic-crud/src/modules/caller/caller_2_service.py
sample/01-basic-crud/src/modules/caller/caller_3_service.py
sample/01-basic-crud/src/modules/caller/caller_service.py
sample/01-basic-crud/src/modules/partner/partner_controller.py
sample/01-basic-crud/src/modules/partner/partner_module.py
sample/01-basic-crud/src/modules/partner/partner_service.py
sample/01-basic-crud/src/modules/partner/dto/create_partner_dto.py
sample/01-basic-crud/src/modules/partner/dto/update_partner_dto.py
modulare-0.0.37.dev0.dist-info/LICENSE.txt
modulare-0.0.37.dev0.dist-info/METADATA
modulare-0.0.37.dev0.dist-info/WHEEL
modulare-0.0.37.dev0.dist-info/top_level.txt
modulare-0.0.37.dev0.dist-info/RECORD
